<annotation>
  <path>TB19S4jLXXXXXXAaFXXunYpLFXX.txt</path>
  <folder/>
  <filename>TB19S4jLXXXXXXAaFXXunYpLFXX</filename>
  <source>
    <database>Unknown</database>
  </source>
  <size>
    <width>800</width>
    <height>800</height>
    <depth>3</depth>
  </size>
  <segmented>segmented</segmented>
  <object>
    <type>robndbox</type>
    <name>malata</name>
    <pose>Unspecified</pose>
    <truncated>0</truncated>
    <difficult>0</difficult>
    <robndbox>
      <cx>475.2</cx>
      <cy>623.0</cy>
      <w>185.90553156519593</w>
      <h>39.890893782037026</h>
      <angle>-0.7654</angle>
    </robndbox>
  </object>
  <object>
    <type>robndbox</type>
    <name>&#26376;&#20809;&#23453;&#30418;</name>
    <pose>Unspecified</pose>
    <truncated>0</truncated>
    <difficult>0</difficult>
    <robndbox>
      <cx>577.5999999999999</cx>
      <cy>516.0</cy>
      <w>109.84359355152937</w>
      <h>24.60753807466929</h>
      <angle>-0.781</angle>
    </robndbox>
  </object>
  <object>
    <type>robndbox</type>
    <name>Moonlightchest</name>
    <pose>Unspecified</pose>
    <truncated>0</truncated>
    <difficult>0</difficult>
    <robndbox>
      <cx>594.2</cx>
      <cy>527.0</cy>
      <w>104.70835527200029</w>
      <h>11.879393923934007</h>
      <angle>-0.7519</angle>
    </robndbox>
  </object>
  <object>
    <type>robndbox</type>
    <name>m</name>
    <pose>Unspecified</pose>
    <truncated>0</truncated>
    <difficult>0</difficult>
    <robndbox>
      <cx>284.79999999999995</cx>
      <cy>634.8</cy>
      <w>32.80000000000001</w>
      <h>28.0</h>
      <angle>0.0</angle>
    </robndbox>
  </object>
  <object>
    <type>robndbox</type>
    <name>m</name>
    <pose>Unspecified</pose>
    <truncated>0</truncated>
    <difficult>0</difficult>
    <robndbox>
      <cx>551.8</cx>
      <cy>304.2</cy>
      <w>30.217249570132097</w>
      <h>21.207404868885057</h>
      <angle>-0.0553</angle>
    </robndbox>
  </object>
  <object>
    <type>robndbox</type>
    <name>02:30</name>
    <pose>Unspecified</pose>
    <truncated>0</truncated>
    <difficult>0</difficult>
    <robndbox>
      <cx>478.80000000000007</cx>
      <cy>325.0</cy>
      <w>77.10971924110981</w>
      <h>26.799999999999983</h>
      <angle>-0.0636</angle>
    </robndbox>
  </object>
  <object>
    <type>robndbox</type>
    <name>&#21378;&#23478;&#30452;&#38144;</name>
    <pose>Unspecified</pose>
    <truncated>0</truncated>
    <difficult>0</difficult>
    <robndbox>
      <cx>137.6</cx>
      <cy>201.6</cy>
      <w>191.2</w>
      <h>46.400000000000006</h>
      <angle>-0.0</angle>
    </robndbox>
  </object>
  <object>
    <type>robndbox</type>
    <name>&#20840;&#22269;&#32852;&#20445;</name>
    <pose>Unspecified</pose>
    <truncated>0</truncated>
    <difficult>0</difficult>
    <robndbox>
      <cx>167.2</cx>
      <cy>136.0</cy>
      <w>252.0</w>
      <h>65.60000000000001</h>
      <angle>-0.0</angle>
    </robndbox>
  </object>
  <object>
    <type>robndbox</type>
    <name>&#19975;&#21033;&#36798;</name>
    <pose>Unspecified</pose>
    <truncated>0</truncated>
    <difficult>0</difficult>
    <robndbox>
      <cx>128.79999999999998</cx>
      <cy>62.8</cy>
      <w>136.79999999999998</w>
      <h>39.2</h>
      <angle>-0.0</angle>
    </robndbox>
  </object>
  <object>
    <type>robndbox</type>
    <name>&#174;</name>
    <pose>Unspecified</pose>
    <truncated>0</truncated>
    <difficult>0</difficult>
    <robndbox>
      <cx>204.40000000000003</cx>
      <cy>51.0</cy>
      <w>12.813318551349175</w>
      <h>11.65685424949238</h>
      <angle>0.0261</angle>
    </robndbox>
  </object>
  <object>
    <type>robndbox</type>
    <name>malata</name>
    <pose>Unspecified</pose>
    <truncated>0</truncated>
    <difficult>0</difficult>
    <robndbox>
      <cx>301.2</cx>
      <cy>63.60000000000001</cy>
      <w>177.6</w>
      <h>37.60000000000001</h>
      <angle>0.0</angle>
    </robndbox>
  </object>
  <object>
    <type>robndbox</type>
    <name>&#174;</name>
    <pose>Unspecified</pose>
    <truncated>0</truncated>
    <difficult>0</difficult>
    <robndbox>
      <cx>396.0</cx>
      <cy>50.8</cy>
      <w>12.0</w>
      <h>13.600000000000001</h>
      <angle>-0.0</angle>
    </robndbox>
  </object>
</annotation>
