<annotation>
  <path>TB1RmXHLXXXXXX_XFXXunYpLFXX.txt</path>
  <folder/>
  <filename>TB1RmXHLXXXXXX_XFXXunYpLFXX</filename>
  <source>
    <database>Unknown</database>
  </source>
  <size>
    <width>800</width>
    <height>800</height>
    <depth>3</depth>
  </size>
  <segmented>segmented</segmented>
  <object>
    <type>robndbox</type>
    <name>&#20013;&#20851;&#26449;&#29615;&#22659;&#31185;&#23398;&#30740;&#31350;&#38498;</name>
    <pose>Unspecified</pose>
    <truncated>0</truncated>
    <difficult>0</difficult>
    <robndbox>
      <cx>294.66999999999996</cx>
      <cy>138.66500000000002</cy>
      <w>507.99999999999994</w>
      <h>45.33000000000001</h>
      <angle>0.0</angle>
    </robndbox>
  </object>
  <object>
    <type>robndbox</type>
    <name>&#27597;&#23156;</name>
    <pose>Unspecified</pose>
    <truncated>0</truncated>
    <difficult>0</difficult>
    <robndbox>
      <cx>563.33</cx>
      <cy>60.66499999999999</cy>
      <w>96.0</w>
      <h>46.67</h>
      <angle>-0.0</angle>
    </robndbox>
  </object>
  <object>
    <type>robndbox</type>
    <name>&#20581;&#24247;</name>
    <pose>Unspecified</pose>
    <truncated>0</truncated>
    <difficult>0</difficult>
    <robndbox>
      <cx>704.665</cx>
      <cy>60.66499999999999</cy>
      <w>93.33000000000004</w>
      <h>46.67</h>
      <angle>0.0</angle>
    </robndbox>
  </object>
  <object>
    <type>robndbox</type>
    <name>&#22269;&#23478;&#32423;&#26426;&#26500;&#26435;&#23041;&#35748;&#35777;&#183;&#32511;&#33394;&#38500;&#21619;</name>
    <pose>Unspecified</pose>
    <truncated>0</truncated>
    <difficult>0</difficult>
    <robndbox>
      <cx>251.33</cx>
      <cy>82.67</cy>
      <w>424.0</w>
      <h>32.0</h>
      <angle>0.0</angle>
    </robndbox>
  </object>
  <object>
    <type>robndbox</type>
    <name>&#31354;&#27668;&#20998;&#35299;&#38500;&#21619;&#21058;</name>
    <pose>Unspecified</pose>
    <truncated>0</truncated>
    <difficult>0</difficult>
    <robndbox>
      <cx>294.4775</cx>
      <cy>355.71500000000003</cy>
      <w>162.32212086338274</w>
      <h>27.484096511979764</h>
      <angle>-0.0256</angle>
    </robndbox>
  </object>
  <object>
    <type>robndbox</type>
    <name>ToiletAirDecompositionDegasiter</name>
    <pose>Unspecified</pose>
    <truncated>0</truncated>
    <difficult>0</difficult>
    <robndbox>
      <cx>292.0</cx>
      <cy>376.8125</cy>
      <w>156.64096469061388</w>
      <h>9.063039429017639</h>
      <angle>0.0251</angle>
    </robndbox>
  </object>
  <object>
    <type>robndbox</type>
    <name>&#24378;&#25928;&#38500;&#21619;</name>
    <pose>Unspecified</pose>
    <truncated>0</truncated>
    <difficult>0</difficult>
    <robndbox>
      <cx>289.33500000000004</cx>
      <cy>406.6675</cy>
      <w>46.6890902672087</w>
      <h>14.664999999999992</h>
      <angle>-0.0258</angle>
    </robndbox>
  </object>
  <object>
    <type>robndbox</type>
    <name>&#36824;&#21407;&#21355;&#28020;</name>
    <pose>Unspecified</pose>
    <truncated>0</truncated>
    <difficult>0</difficult>
    <robndbox>
      <cx>460.6675</cx>
      <cy>371.3325</cy>
      <w>57.37867819852825</w>
      <h>15.625915807459243</h>
      <angle>-0.543</angle>
    </robndbox>
  </object>
  <object>
    <type>robndbox</type>
    <name>&#26032;&#40092;&#31354;</name>
    <pose>Unspecified</pose>
    <truncated>0</truncated>
    <difficult>0</difficult>
    <robndbox>
      <cx>507.335</cx>
      <cy>353.33500000000004</cy>
      <w>42.66999999999996</w>
      <h>13.329999999999984</h>
      <angle>0.0</angle>
    </robndbox>
  </object>
  <object>
    <type>robndbox</type>
    <name>&#27668;</name>
    <pose>Unspecified</pose>
    <truncated>0</truncated>
    <difficult>0</difficult>
    <robndbox>
      <cx>538.665</cx>
      <cy>357.33</cy>
      <w>14.669999999999959</w>
      <h>16.0</h>
      <angle>0.0</angle>
    </robndbox>
  </object>
  <object>
    <type>robndbox</type>
    <name>&#29233;&#23478;&#65292;</name>
    <pose>Unspecified</pose>
    <truncated>0</truncated>
    <difficult>0</difficult>
    <robndbox>
      <cx>423.33500000000004</cx>
      <cy>248.665</cy>
      <w>42.670000000000016</w>
      <h>17.329999999999984</h>
      <angle>-0.0</angle>
    </robndbox>
  </object>
  <object>
    <type>robndbox</type>
    <name>&#26356;&#29233;&#22320;&#29699;</name>
    <pose>Unspecified</pose>
    <truncated>0</truncated>
    <difficult>0</difficult>
    <robndbox>
      <cx>509.33500000000004</cx>
      <cy>244.66500000000002</cy>
      <w>105.40592440655315</w>
      <h>21.33</h>
      <angle>-0.0363</angle>
    </robndbox>
  </object>
  <object>
    <type>robndbox</type>
    <name>400-0857-668</name>
    <pose>Unspecified</pose>
    <truncated>0</truncated>
    <difficult>0</difficult>
    <robndbox>
      <cx>335.33500000000004</cx>
      <cy>244.99750000000003</cy>
      <w>85.39734444618125</w>
      <h>12.810640731445343</h>
      <angle>-0.0321</angle>
    </robndbox>
  </object>
  <object>
    <type>robndbox</type>
    <name>&#21355;&#29983;&#38388;&#19987;&#29992;</name>
    <pose>Unspecified</pose>
    <truncated>0</truncated>
    <difficult>0</difficult>
    <robndbox>
      <cx>522.0</cx>
      <cy>637.335</cy>
      <w>461.34</w>
      <h>85.33000000000004</h>
      <angle>0.0</angle>
    </robndbox>
  </object>
  <object>
    <type>robndbox</type>
    <name>&#27597;&#23156;&#23433;&#20840;&#38500;&#21619;</name>
    <pose>Unspecified</pose>
    <truncated>0</truncated>
    <difficult>0</difficult>
    <robndbox>
      <cx>536.0</cx>
      <cy>731.335</cy>
      <w>425.34</w>
      <h>62.66999999999996</h>
      <angle>0.0</angle>
    </robndbox>
  </object>
  <object>
    <type>robndbox</type>
    <name>&#30456;&#20449;&#21697;&#29260;&#30340;&#21147;&#37327;</name>
    <pose>Unspecified</pose>
    <truncated>0</truncated>
    <difficult>0</difficult>
    <robndbox>
      <cx>146.67</cx>
      <cy>730.0</cy>
      <w>196.0</w>
      <h>30.660000000000082</h>
      <angle>0.0</angle>
    </robndbox>
  </object>
  <object>
    <type>robndbox</type>
    <name>&#29233;&#22320;&#29699;</name>
    <pose>Unspecified</pose>
    <truncated>0</truncated>
    <difficult>0</difficult>
    <robndbox>
      <cx>133.335</cx>
      <cy>690.0</cy>
      <w>121.33</w>
      <h>25.339999999999918</h>
      <angle>-0.0</angle>
    </robndbox>
  </object>
  <object>
    <type>robndbox</type>
    <name>www.idiqiu.net</name>
    <pose>Unspecified</pose>
    <truncated>0</truncated>
    <difficult>0</difficult>
    <robndbox>
      <cx>334.66499999999996</cx>
      <cy>262.0</cy>
      <w>86.7622550421553</w>
      <h>10.659999999999982</h>
      <angle>-0.0453</angle>
    </robndbox>
  </object>
  <object>
    <type>robndbox</type>
    <name>&#29233;&#22320;&#29699;</name>
    <pose>Unspecified</pose>
    <truncated>0</truncated>
    <difficult>0</difficult>
    <robndbox>
      <cx>192.0</cx>
      <cy>275.33500000000004</cy>
      <w>33.339999999999975</w>
      <h>9.329999999999984</h>
      <angle>0.0</angle>
    </robndbox>
  </object>
  <object>
    <type>robndbox</type>
    <name>&#21355;&#29983;&#38388;</name>
    <pose>Unspecified</pose>
    <truncated>0</truncated>
    <difficult>0</difficult>
    <robndbox>
      <cx>262.67</cx>
      <cy>326.0</cy>
      <w>60.00000000000003</w>
      <h>22.659999999999968</h>
      <angle>-0.0</angle>
    </robndbox>
  </object>
  <object>
    <type>robndbox</type>
    <name>&#39640;&#25928;&#20998;&#35299;</name>
    <pose>Unspecified</pose>
    <truncated>0</truncated>
    <difficult>0</difficult>
    <robndbox>
      <cx>351.33500000000004</cx>
      <cy>407.33500000000004</cy>
      <w>50.670000000000016</w>
      <h>14.670000000000016</h>
      <angle>0.0</angle>
    </robndbox>
  </object>
  <object>
    <type>robndbox</type>
    <name>&#26377;&#23475;</name>
    <pose>Unspecified</pose>
    <truncated>0</truncated>
    <difficult>0</difficult>
    <robndbox>
      <cx>390.0</cx>
      <cy>410.0</cy>
      <w>18.659999999999968</w>
      <h>14.659999999999968</h>
      <angle>0.0</angle>
    </robndbox>
  </object>
  <object>
    <type>robndbox</type>
    <name>&#27668;&#20307;</name>
    <pose>Unspecified</pose>
    <truncated>0</truncated>
    <difficult>0</difficult>
    <robndbox>
      <cx>412.6675</cx>
      <cy>407.67</cy>
      <w>27.401363130849397</w>
      <h>14.256264936770105</h>
      <angle>-0.1516</angle>
    </robndbox>
  </object>
  <object>
    <type>robndbox</type>
    <name>&#174;</name>
    <pose>Unspecified</pose>
    <truncated>0</truncated>
    <difficult>0</difficult>
    <robndbox>
      <cx>168.365</cx>
      <cy>590.9100000000001</cy>
      <w>20.370000000000005</w>
      <h>19.639999999999986</h>
      <angle>0.0</angle>
    </robndbox>
  </object>
  <object>
    <type>robndbox</type>
    <name>&#21271;&#20140;&#8226;&#20013;&#20851;&#26449;&#39640;&#26032;&#25216;&#26415;&#20225;&#19994;</name>
    <pose>Unspecified</pose>
    <truncated>0</truncated>
    <difficult>0</difficult>
    <robndbox>
      <cx>381.71500000000003</cx>
      <cy>475.28499999999997</cy>
      <w>98.16424580705193</w>
      <h>10.03150848399188</h>
      <angle>0.0925</angle>
    </robndbox>
  </object>
</annotation>
