<annotation>
  <path>TB1LpR0omYH8KJjSspdXXcRgVXa_!!0-item_pic.jpg.txt</path>
  <folder/>
  <filename>TB1LpR0omYH8KJjSspdXXcRgVXa_!!0-item_pic</filename>
  <source>
    <database>Unknown</database>
  </source>
  <size>
    <width>400</width>
    <height>400</height>
    <depth>3</depth>
  </size>
  <segmented>segmented</segmented>
  <object>
    <type>robndbox</type>
    <name>&#28909;&#21334;&#20013;</name>
    <pose>Unspecified</pose>
    <truncated>0</truncated>
    <difficult>0</difficult>
    <robndbox>
      <cx>350.6</cx>
      <cy>236.2</cy>
      <w>72.0</w>
      <h>20.400000000000006</h>
      <angle>-0.0</angle>
    </robndbox>
  </object>
  <object>
    <type>robndbox</type>
    <name>&#38450;&#30701;&#36335;</name>
    <pose>Unspecified</pose>
    <truncated>0</truncated>
    <difficult>0</difficult>
    <robndbox>
      <cx>67.8</cx>
      <cy>372.2</cy>
      <w>108.8</w>
      <h>40.39999999999998</h>
      <angle>0.0</angle>
    </robndbox>
  </object>
  <object>
    <type>robndbox</type>
    <name>&#24102;&#24320;&#20851;</name>
    <pose>Unspecified</pose>
    <truncated>0</truncated>
    <difficult>0</difficult>
    <robndbox>
      <cx>193.39999999999998</cx>
      <cy>369.6</cy>
      <w>107.19999999999999</w>
      <h>40.80000000000001</h>
      <angle>0.0</angle>
    </robndbox>
  </object>
  <object>
    <type>robndbox</type>
    <name>&#36865;&#36192;&#21697;</name>
    <pose>Unspecified</pose>
    <truncated>0</truncated>
    <difficult>0</difficult>
    <robndbox>
      <cx>321.6</cx>
      <cy>369.79999999999995</cy>
      <w>112.40000000000003</w>
      <h>38.80000000000001</h>
      <angle>-0.0</angle>
    </robndbox>
  </object>
  <object>
    <type>robndbox</type>
    <name>&#19977;&#23380;&#28857;&#28895;&#22120;</name>
    <pose>Unspecified</pose>
    <truncated>0</truncated>
    <difficult>0</difficult>
    <robndbox>
      <cx>117.20000000000002</cx>
      <cy>38.4</cy>
      <w>205.20000000000002</w>
      <h>48.0</h>
      <angle>-0.0</angle>
    </robndbox>
  </object>
  <object>
    <type>robndbox</type>
    <name>&#21452;USB</name>
    <pose>Unspecified</pose>
    <truncated>0</truncated>
    <difficult>0</difficult>
    <robndbox>
      <cx>315.0</cx>
      <cy>35.0</cy>
      <w>159.20000000000002</w>
      <h>42.0</h>
      <angle>0.0</angle>
    </robndbox>
  </object>
</annotation>
